["{\"type\":\"list\",\"attributes\":{\"names\":{\"type\":\"character\",\"attributes\":{},\"value\":[\"pred\",\"interval\",\"level\",\"global\",\"type\",\"method\",\"B\",\"estim\",\"B_estim\",\"warning_messages\",\"median\",\"moon\",\"model\",\"dataset\",\"species\",\"old_cast_id\",\"cast_id\"]}},\"value\":[{\"type\":\"double\",\"attributes\":{},\"value\":[0.74133654,0.5729407,0.30187779,0.29159837,0.58984868,0.32958817,0.27653539,0.38880532,0.26459614,0.23022661,0.22544666,0.35340137,0.41885364,0.42843263,0.4094365]},{\"type\":\"integer\",\"attributes\":{\"dim\":{\"type\":\"integer\",\"attributes\":{},\"value\":[15,2]},\"dimnames\":{\"type\":\"list\",\"attributes\":{},\"value\":[{\"type\":\"NULL\"},{\"type\":\"character\",\"attributes\":{},\"value\":[\"lower\",\"upper\"]}]}},\"value\":[0,0,0,0,0,0,0,0,0,0,0,0,0,0,0,3,3,2,2,3,2,2,2,1,1,1,2,2,2,2]},{\"type\":\"double\",\"attributes\":{},\"value\":[0.95]},{\"type\":\"logical\",\"attributes\":{},\"value\":[false]},{\"type\":\"character\",\"attributes\":{},\"value\":[\"quantiles\"]},{\"type\":\"character\",\"attributes\":{},\"value\":[\"bootstrap\"]},{\"type\":\"double\",\"attributes\":{},\"value\":[1000]},{\"type\":\"character\",\"attributes\":{},\"value\":[\"ignore\"]},{\"type\":\"double\",\"attributes\":{},\"value\":[0]},{\"type\":\"character\",\"attributes\":{},\"value\":[]},{\"type\":\"double\",\"attributes\":{},\"value\":[1,0,0,0,0,0,0,0,0,0,0,0,0,0,0]},{\"type\":\"integer\",\"attributes\":{},\"value\":[528,529,530,531,532,533,534,535,536,537,538,539,540,541,542]},{\"type\":\"character\",\"attributes\":{},\"value\":[\"pevGARCH\"]},{\"type\":\"character\",\"attributes\":{},\"value\":[\"controls\"]},{\"type\":\"character\",\"attributes\":{},\"value\":[\"PE\"]},{\"type\":\"integer\",\"attributes\":{},\"value\":[827]},{\"type\":\"character\",\"attributes\":{},\"value\":[\"827.9\"]}]}"]
