["{\"type\":\"list\",\"attributes\":{\"names\":{\"type\":\"character\",\"attributes\":{},\"value\":[\"Point.Forecast\",\"Lo.95\",\"Hi.95\",\"moon\",\"model\",\"dataset\",\"species\",\"old_cast_id\",\"cast_id\"]}},\"value\":[{\"type\":\"double\",\"attributes\":{},\"value\":[2,2,2,2,2,2,2,2,2,2,2,2,2]},{\"type\":\"double\",\"attributes\":{},\"value\":[-7.77828004,-11.82857625,-14.93647784,-17.55656008,-19.86489887,-21.95179666,-23.87089724,-25.6571525,-27.33484012,-28.92163653,-30.43088599,-31.87295568,-33.25609007]},{\"type\":\"double\",\"attributes\":{},\"value\":[11.77828004,15.82857625,18.93647784,21.55656008,23.86489887,25.95179666,27.87089724,29.6571525,31.33484012,32.92163653,34.43088599,35.87295568,37.25609007]},{\"type\":\"integer\",\"attributes\":{},\"value\":[565,566,567,568,569,570,571,572,573,574,575,576,577]},{\"type\":\"character\",\"attributes\":{},\"value\":[\"NaiveArima\"]},{\"type\":\"character\",\"attributes\":{},\"value\":[\"exclosures\"]},{\"type\":\"character\",\"attributes\":{},\"value\":[\"PE\"]},{\"type\":\"integer\",\"attributes\":{},\"value\":[3059]},{\"type\":\"character\",\"attributes\":{},\"value\":[\"3059.7\"]}]}"]
