["{\"type\":\"list\",\"attributes\":{\"names\":{\"type\":\"character\",\"attributes\":{},\"value\":[\"pred\",\"interval\",\"level\",\"global\",\"type\",\"method\",\"B\",\"estim\",\"B_estim\",\"warning_messages\",\"median\",\"moon\",\"model\",\"dataset\",\"species\",\"old_cast_id\",\"cast_id\"]}},\"value\":[{\"type\":\"double\",\"attributes\":{\"tsp\":{\"type\":\"double\",\"attributes\":{},\"value\":[344,356,1]},\"class\":{\"type\":\"character\",\"attributes\":{},\"value\":[\"ts\"]}},\"value\":[0.10993426,0.12255425,0.11076838,0.08975863,0.06835964,0.05320648,0.04527275,0.04335964,0.04728735,0.05765196,0.07406431,0.09579601,0.1152071]},{\"type\":\"double\",\"attributes\":{\"dim\":{\"type\":\"integer\",\"attributes\":{},\"value\":[13,2]},\"dimnames\":{\"type\":\"list\",\"attributes\":{},\"value\":[{\"type\":\"NULL\"},{\"type\":\"character\",\"attributes\":{},\"value\":[\"lower\",\"upper\"]}]},\"tsp\":{\"type\":\"double\",\"attributes\":{},\"value\":[344,356,1]},\"class\":{\"type\":\"character\",\"attributes\":{},\"value\":[\"mts\",\"ts\",\"matrix\"]}},\"value\":[0,0,0,0,0,0,0,0,0,0,0,0,0,1,1,1,1,1,1,1,1,1,1,1,1,1]},{\"type\":\"double\",\"attributes\":{},\"value\":[0.95]},{\"type\":\"logical\",\"attributes\":{},\"value\":[false]},{\"type\":\"character\",\"attributes\":{},\"value\":[\"quantiles\"]},{\"type\":\"character\",\"attributes\":{},\"value\":[\"bootstrap\"]},{\"type\":\"double\",\"attributes\":{},\"value\":[1000]},{\"type\":\"character\",\"attributes\":{},\"value\":[\"ignore\"]},{\"type\":\"double\",\"attributes\":{},\"value\":[0]},{\"type\":\"character\",\"attributes\":{},\"value\":[]},{\"type\":\"double\",\"attributes\":{\"tsp\":{\"type\":\"double\",\"attributes\":{},\"value\":[344,356,1]},\"class\":{\"type\":\"character\",\"attributes\":{},\"value\":[\"ts\"]}},\"value\":[0,0,0,0,0,0,0,0,0,0,0,0,0]},{\"type\":\"integer\",\"attributes\":{},\"value\":[560,561,562,563,564,565,566,567,568,569,570,571,572]},{\"type\":\"character\",\"attributes\":{},\"value\":[\"nbsGARCH\"]},{\"type\":\"character\",\"attributes\":{},\"value\":[\"controls\"]},{\"type\":\"character\",\"attributes\":{},\"value\":[\"DS\"]},{\"type\":\"integer\",\"attributes\":{},\"value\":[2993]},{\"type\":\"character\",\"attributes\":{},\"value\":[\"2993.4\"]}]}"]
