["{\"type\":\"list\",\"attributes\":{\"names\":{\"type\":\"character\",\"attributes\":{},\"value\":[\"Point.Forecast\",\"Lo.95\",\"Hi.95\",\"moon\",\"model\",\"dataset\",\"species\",\"old_cast_id\",\"cast_id\"]}},\"value\":[{\"type\":\"double\",\"attributes\":{},\"value\":[0,0,0,0,0,0,0,0,0,0,0,0,0]},{\"type\":\"double\",\"attributes\":{},\"value\":[-1.88847937,-2.67071314,-3.27094223,-3.77695875,-4.22276826,-4.62581086,-4.99644678,-5.34142629,-5.66543812,-5.97189614,-6.26337751,-6.54188445,-6.80900922]},{\"type\":\"double\",\"attributes\":{},\"value\":[1.88847937,2.67071314,3.27094223,3.77695875,4.22276826,4.62581086,4.99644678,5.34142629,5.66543812,5.97189614,6.26337751,6.54188445,6.80900922]},{\"type\":\"integer\",\"attributes\":{},\"value\":[527,528,529,530,531,532,533,534,535,536,537,538,539]},{\"type\":\"character\",\"attributes\":{},\"value\":[\"NaiveArima\"]},{\"type\":\"character\",\"attributes\":{},\"value\":[\"all\"]},{\"type\":\"character\",\"attributes\":{},\"value\":[\"RO\"]},{\"type\":\"integer\",\"attributes\":{},\"value\":[448]},{\"type\":\"character\",\"attributes\":{},\"value\":[\"448.17\"]}]}"]
