["{\"type\":\"list\",\"attributes\":{\"names\":{\"type\":\"character\",\"attributes\":{},\"value\":[\"Point.Forecast\",\"Lo.95\",\"Hi.95\",\"moon\",\"model\",\"dataset\",\"species\",\"old_cast_id\",\"cast_id\"]}},\"value\":[{\"type\":\"double\",\"attributes\":{},\"value\":[0.032,0.036,0.041,0.045,0.05,0.056,0.06,0.065,0.071,0.078,0.084,0.089,0.093,0.099]},{\"type\":\"double\",\"attributes\":{},\"value\":[0,0,0,0,0,0,0,0,0,0,0,0,0,0]},{\"type\":\"double\",\"attributes\":{},\"value\":[0.168,0.188,0.206,0.23,0.252,0.268,0.287,0.31,0.337,0.361,0.384,0.41,0.433,0.46]},{\"type\":\"integer\",\"attributes\":{},\"value\":[524,525,526,527,528,529,530,531,532,533,534,535,536,537]},{\"type\":\"character\",\"attributes\":{},\"value\":[\"jags_RW\"]},{\"type\":\"character\",\"attributes\":{},\"value\":[\"exclosures\"]},{\"type\":\"character\",\"attributes\":{},\"value\":[\"PL\"]},{\"type\":\"integer\",\"attributes\":{},\"value\":[165]},{\"type\":\"character\",\"attributes\":{},\"value\":[\"165.11\"]}]}"]
