["{\"type\":\"list\",\"attributes\":{\"names\":{\"type\":\"character\",\"attributes\":{},\"value\":[\"Point.Forecast\",\"Lo.95\",\"Hi.95\",\"moon\",\"model\",\"dataset\",\"species\",\"old_cast_id\",\"cast_id\"]}},\"value\":[{\"type\":\"double\",\"attributes\":{},\"value\":[2.64403702,3.15520361,3.8785927,4.5001737,4.5001737,4.5001737,4.5001737,4.5001737,4.5001737,4.5001737,4.5001737,4.5001737]},{\"type\":\"double\",\"attributes\":{},\"value\":[-8.62305264,-12.64474106,-13.6209093,-13.48535698,-13.48535698,-13.48535698,-13.48535698,-13.48535698,-13.48535698,-13.48535698,-13.48535698,-13.48535698]},{\"type\":\"double\",\"attributes\":{},\"value\":[13.91112668,18.95514827,21.3780947,22.48570438,22.48570438,22.48570438,22.48570438,22.48570438,22.48570438,22.48570438,22.48570438,22.48570438]},{\"type\":\"integer\",\"attributes\":{},\"value\":[528,529,530,531,532,533,534,535,536,537,538,539]},{\"type\":\"character\",\"attributes\":{},\"value\":[\"AutoArima\"]},{\"type\":\"character\",\"attributes\":{},\"value\":[\"all\"]},{\"type\":\"character\",\"attributes\":{},\"value\":[\"RM\"]},{\"type\":\"integer\",\"attributes\":{},\"value\":[541]},{\"type\":\"character\",\"attributes\":{},\"value\":[\"541.16\"]}]}"]
