["{\"type\":\"list\",\"attributes\":{\"names\":{\"type\":\"character\",\"attributes\":{},\"value\":[\"Point.Forecast\",\"Lo.95\",\"Hi.95\",\"moon\",\"model\",\"dataset\",\"species\",\"old_cast_id\",\"cast_id\"]}},\"value\":[{\"type\":\"double\",\"attributes\":{},\"value\":[0.211,0.531,1.146,2.117,3.403,4.943,6.258,7.751,9.102,10.123,11.339,12.723,13.625,14.426,15.336,15.575,16.331,16.687,17.177,17.559]},{\"type\":\"double\",\"attributes\":{},\"value\":[0,0,0,0,0,0,0,0,0,0,0,0,0,0,0,0,0,0,0,0]},{\"type\":\"double\",\"attributes\":{},\"value\":[0.933,2.269,4.442,7.538,12.506,18.946,28.7,38.528,51.597,63.621,75.973,98.409,105.275,120.709,131.943,131.364,144.492,147.132,149.762,157.972]},{\"type\":\"integer\",\"attributes\":{},\"value\":[528,529,530,531,532,533,534,535,536,537,538,539,540,541,542,543,544,545,546,547]},{\"type\":\"character\",\"attributes\":{},\"value\":[\"jags_RW\"]},{\"type\":\"character\",\"attributes\":{},\"value\":[\"exclosures\"]},{\"type\":\"character\",\"attributes\":{},\"value\":[\"RF\"]},{\"type\":\"integer\",\"attributes\":{},\"value\":[1302]},{\"type\":\"character\",\"attributes\":{},\"value\":[\"1302.14\"]}]}"]
