["{\"type\":\"list\",\"attributes\":{\"names\":{\"type\":\"character\",\"attributes\":{},\"value\":[\"Point.Forecast\",\"Lo.95\",\"Hi.95\",\"moon\",\"model\",\"dataset\",\"species\",\"old_cast_id\",\"cast_id\"]}},\"value\":[{\"type\":\"double\",\"attributes\":{},\"value\":[5.243,8.238,13.1,19.805,29.045,39.169,49.827,59.692,69.794,79.78,87.534,96.592,102.949,111.953,118.677]},{\"type\":\"double\",\"attributes\":{},\"value\":[1.56,0,0,0,0,0,0,0,0,0,0,0,0,0,0]},{\"type\":\"double\",\"attributes\":{},\"value\":[9.448,26.564,48.59,77.303,120.017,169.65,233.899,310.875,393.9,495.088,575.782,668.05,734.1,847.513,954.325]},{\"type\":\"integer\",\"attributes\":{},\"value\":[528,529,530,531,532,533,534,535,536,537,538,539,540,541,542]},{\"type\":\"character\",\"attributes\":{},\"value\":[\"jags_RW\"]},{\"type\":\"character\",\"attributes\":{},\"value\":[\"all\"]},{\"type\":\"character\",\"attributes\":{},\"value\":[\"DO\"]},{\"type\":\"integer\",\"attributes\":{},\"value\":[814]},{\"type\":\"character\",\"attributes\":{},\"value\":[\"814.3\"]}]}"]
