["{\"type\":\"list\",\"attributes\":{\"names\":{\"type\":\"character\",\"attributes\":{},\"value\":[\"Point.Forecast\",\"Lo.95\",\"Hi.95\",\"moon\",\"model\",\"dataset\",\"species\",\"old_cast_id\",\"cast_id\"]}},\"value\":[{\"type\":\"double\",\"attributes\":{},\"value\":[0.009,0.018,0.032,0.058,0.091,0.135,0.21,0.258,0.352,0.481,0.578,0.728,0.858,0.999,1.166,1.339,1.47,1.582,1.804,1.859,2.084]},{\"type\":\"double\",\"attributes\":{},\"value\":[0,0,0,0,0,0,0,0,0,0,0,0,0,0,0,0,0,0,0,0,0]},{\"type\":\"double\",\"attributes\":{},\"value\":[0.015,0.042,0.072,0.112,0.154,0.201,0.277,0.355,0.458,0.534,0.623,0.782,0.869,1.027,1.22,1.401,1.505,1.69,2.1,2.357,2.872]},{\"type\":\"integer\",\"attributes\":{},\"value\":[528,529,530,531,532,533,534,535,536,537,538,539,540,541,542,543,544,545,546,547,548]},{\"type\":\"character\",\"attributes\":{},\"value\":[\"jags_RW\"]},{\"type\":\"character\",\"attributes\":{},\"value\":[\"controls\"]},{\"type\":\"character\",\"attributes\":{},\"value\":[\"SF\"]},{\"type\":\"integer\",\"attributes\":{},\"value\":[1328]},{\"type\":\"character\",\"attributes\":{},\"value\":[\"1328.16\"]}]}"]
