["{\"type\":\"list\",\"attributes\":{\"names\":{\"type\":\"character\",\"attributes\":{},\"value\":[\"pred\",\"interval\",\"level\",\"global\",\"type\",\"method\",\"B\",\"estim\",\"B_estim\",\"warning_messages\",\"median\",\"moon\",\"model\",\"dataset\",\"species\",\"old_cast_id\",\"cast_id\"]}},\"value\":[{\"type\":\"double\",\"attributes\":{},\"value\":[9.30048749e-19,9.30048749e-19,9.30048749e-19,9.30048749e-19,9.30048749e-19,9.30048749e-19,9.30048749e-19,0.00008119,0.0000812,0.0000812,0.0000812,0.00020802,0.00008121,0.0000812]},{\"type\":\"integer\",\"attributes\":{\"dim\":{\"type\":\"integer\",\"attributes\":{},\"value\":[14,2]},\"dimnames\":{\"type\":\"list\",\"attributes\":{},\"value\":[{\"type\":\"NULL\"},{\"type\":\"character\",\"attributes\":{},\"value\":[\"lower\",\"upper\"]}]}},\"value\":[0,0,0,0,0,0,0,0,0,0,0,0,0,0,0,0,0,0,0,0,0,0,0,0,0,0,0,0]},{\"type\":\"double\",\"attributes\":{},\"value\":[0.95]},{\"type\":\"logical\",\"attributes\":{},\"value\":[false]},{\"type\":\"character\",\"attributes\":{},\"value\":[\"quantiles\"]},{\"type\":\"character\",\"attributes\":{},\"value\":[\"bootstrap\"]},{\"type\":\"double\",\"attributes\":{},\"value\":[1000]},{\"type\":\"character\",\"attributes\":{},\"value\":[\"ignore\"]},{\"type\":\"double\",\"attributes\":{},\"value\":[0]},{\"type\":\"character\",\"attributes\":{},\"value\":[]},{\"type\":\"double\",\"attributes\":{},\"value\":[0,0,0,0,0,0,0,0,0,0,0,0,0,0]},{\"type\":\"integer\",\"attributes\":{},\"value\":[528,529,530,531,532,533,534,535,536,537,538,539,540,541]},{\"type\":\"character\",\"attributes\":{},\"value\":[\"nbGARCH\"]},{\"type\":\"character\",\"attributes\":{},\"value\":[\"all\"]},{\"type\":\"character\",\"attributes\":{},\"value\":[\"SO\"]},{\"type\":\"integer\",\"attributes\":{},\"value\":[712]},{\"type\":\"character\",\"attributes\":{},\"value\":[\"712.20\"]}]}"]
