["{\"type\":\"list\",\"attributes\":{\"names\":{\"type\":\"character\",\"attributes\":{},\"value\":[\"pred\",\"interval\",\"level\",\"global\",\"type\",\"method\",\"B\",\"estim\",\"B_estim\",\"warning_messages\",\"median\",\"moon\",\"model\",\"dataset\",\"species\",\"old_cast_id\",\"cast_id\"]}},\"value\":[{\"type\":\"double\",\"attributes\":{},\"value\":[1.12316668,2.40790285,3.67114154,5.63479741,10.67113489,12.99431193,14.8694314,18.04894314,15.92253071,11.23477682,7.70796598,5.76200549,4.71596156,4.68044043,4.99132723]},{\"type\":\"integer\",\"attributes\":{\"dim\":{\"type\":\"integer\",\"attributes\":{},\"value\":[15,2]},\"dimnames\":{\"type\":\"list\",\"attributes\":{},\"value\":[{\"type\":\"NULL\"},{\"type\":\"character\",\"attributes\":{},\"value\":[\"lower\",\"upper\"]}]}},\"value\":[0,0,0,0,2,3,4,6,5,3,2,1,0,0,0,3,7,9,13,22,25,28,32,27,21,16,13,11,11,11]},{\"type\":\"double\",\"attributes\":{},\"value\":[0.95]},{\"type\":\"logical\",\"attributes\":{},\"value\":[false]},{\"type\":\"character\",\"attributes\":{},\"value\":[\"quantiles\"]},{\"type\":\"character\",\"attributes\":{},\"value\":[\"bootstrap\"]},{\"type\":\"double\",\"attributes\":{},\"value\":[1000]},{\"type\":\"character\",\"attributes\":{},\"value\":[\"ignore\"]},{\"type\":\"double\",\"attributes\":{},\"value\":[0]},{\"type\":\"character\",\"attributes\":{},\"value\":[]},{\"type\":\"double\",\"attributes\":{},\"value\":[1,2,3,5,9,12,14,16,14,10,7,5,4,4,4]},{\"type\":\"integer\",\"attributes\":{},\"value\":[528,529,530,531,532,533,534,535,536,537,538,539,540,541,542]},{\"type\":\"character\",\"attributes\":{},\"value\":[\"pevGARCH\"]},{\"type\":\"character\",\"attributes\":{},\"value\":[\"controls\"]},{\"type\":\"character\",\"attributes\":{},\"value\":[\"RM\"]},{\"type\":\"integer\",\"attributes\":{},\"value\":[800]},{\"type\":\"character\",\"attributes\":{},\"value\":[\"800.14\"]}]}"]
