["{\"type\":\"list\",\"attributes\":{\"names\":{\"type\":\"character\",\"attributes\":{},\"value\":[\"Point.Forecast\",\"Lo.95\",\"Hi.95\",\"moon\",\"model\",\"dataset\",\"species\",\"old_cast_id\",\"cast_id\"]}},\"value\":[{\"type\":\"double\",\"attributes\":{},\"value\":[0.006,0.01,0.013,0.019,0.023,0.029,0.038,0.047,0.057,0.067,0.076,0.092,0.108]},{\"type\":\"double\",\"attributes\":{},\"value\":[0,0,0,0,0,0,0,0,0,0,0,0,0]},{\"type\":\"double\",\"attributes\":{},\"value\":[0.02,0.035,0.051,0.067,0.082,0.1,0.123,0.147,0.181,0.201,0.229,0.26,0.289]},{\"type\":\"integer\",\"attributes\":{},\"value\":[527,528,529,530,531,532,533,534,535,536,537,538,539]},{\"type\":\"character\",\"attributes\":{},\"value\":[\"jags_RW\"]},{\"type\":\"character\",\"attributes\":{},\"value\":[\"controls\"]},{\"type\":\"character\",\"attributes\":{},\"value\":[\"PF\"]},{\"type\":\"integer\",\"attributes\":{},\"value\":[422]},{\"type\":\"character\",\"attributes\":{},\"value\":[\"422.10\"]}]}"]
