["{\"type\":\"list\",\"attributes\":{\"names\":{\"type\":\"character\",\"attributes\":{},\"value\":[\"Point.Forecast\",\"Lo.95\",\"Hi.95\",\"moon\",\"model\",\"dataset\",\"species\",\"old_cast_id\",\"cast_id\"]}},\"value\":[{\"type\":\"double\",\"attributes\":{},\"value\":[0.402,1.965,7.041,16.296,28.428,39.799,51.008,62.004,73.649,81.557,88.578,92.283]},{\"type\":\"double\",\"attributes\":{},\"value\":[0,0,0,0,0,0,0,0,0,0,0,0]},{\"type\":\"double\",\"attributes\":{},\"value\":[1.49,7.622,20.86,49.055,98.285,174.306,272.624,405.663,571.662,713.29,856.026,908.508]},{\"type\":\"integer\",\"attributes\":{},\"value\":[528,529,530,531,532,533,534,535,536,537,538,539]},{\"type\":\"character\",\"attributes\":{},\"value\":[\"jags_RW\"]},{\"type\":\"character\",\"attributes\":{},\"value\":[\"all\"]},{\"type\":\"character\",\"attributes\":{},\"value\":[\"PP\"]},{\"type\":\"integer\",\"attributes\":{},\"value\":[574]},{\"type\":\"character\",\"attributes\":{},\"value\":[\"574.14\"]}]}"]
