["{\"type\":\"list\",\"attributes\":{\"names\":{\"type\":\"character\",\"attributes\":{},\"value\":[\"Point.Forecast\",\"Lo.95\",\"Hi.95\",\"moon\",\"model\",\"dataset\",\"species\",\"old_cast_id\",\"cast_id\"]}},\"value\":[{\"type\":\"double\",\"attributes\":{},\"value\":[0.02,0.041,0.086,0.143,0.209,0.354,0.506,0.666,0.853,1.326,1.721,2.062,2.418,3.182,3.823]},{\"type\":\"double\",\"attributes\":{},\"value\":[0,0,0,0,0,0,0,0,0,0,0,0,0,0,0]},{\"type\":\"double\",\"attributes\":{},\"value\":[0.113,0.201,0.291,0.431,0.566,0.72,0.878,1.112,1.388,1.751,2.053,2.449,2.961,3.853,4.548]},{\"type\":\"integer\",\"attributes\":{},\"value\":[528,529,530,531,532,533,534,535,536,537,538,539,540,541,542]},{\"type\":\"character\",\"attributes\":{},\"value\":[\"jags_RW\"]},{\"type\":\"character\",\"attributes\":{},\"value\":[\"all\"]},{\"type\":\"character\",\"attributes\":{},\"value\":[\"PM\"]},{\"type\":\"integer\",\"attributes\":{},\"value\":[760]},{\"type\":\"character\",\"attributes\":{},\"value\":[\"760.13\"]}]}"]
