["{\"type\":\"list\",\"attributes\":{\"names\":{\"type\":\"character\",\"attributes\":{},\"value\":[\"Point.Forecast\",\"Lo.95\",\"Hi.95\",\"moon\",\"model\",\"dataset\",\"species\",\"old_cast_id\",\"cast_id\"]}},\"value\":[{\"type\":\"double\",\"attributes\":{},\"value\":[0.2,0.249,0.306,0.373,0.442,0.539,0.645,0.755,0.9,1.043,1.236,1.426,1.653,1.881,2.02,2.271]},{\"type\":\"double\",\"attributes\":{},\"value\":[0,0,0,0,0,0,0,0,0,0,0,0,0,0,0,0]},{\"type\":\"double\",\"attributes\":{},\"value\":[0.719,0.976,1.246,1.56,1.918,2.278,2.737,3.172,3.724,4.319,4.903,5.495,6.25,6.793,7.622,8.243]},{\"type\":\"integer\",\"attributes\":{},\"value\":[528,529,530,531,532,533,534,535,536,537,538,539,540,541,542,543]},{\"type\":\"character\",\"attributes\":{},\"value\":[\"jags_RW\"]},{\"type\":\"character\",\"attributes\":{},\"value\":[\"exclosures\"]},{\"type\":\"character\",\"attributes\":{},\"value\":[\"PB\"]},{\"type\":\"integer\",\"attributes\":{},\"value\":[843]},{\"type\":\"character\",\"attributes\":{},\"value\":[\"843.7\"]}]}"]
