["{\"type\":\"list\",\"attributes\":{\"names\":{\"type\":\"character\",\"attributes\":{},\"value\":[\"Point.Forecast\",\"Lo.95\",\"Hi.95\",\"moon\",\"model\",\"dataset\",\"species\",\"old_cast_id\",\"cast_id\"]}},\"value\":[{\"type\":\"double\",\"attributes\":{},\"value\":[0.024,0.037,0.051,0.073,0.098,0.131,0.163,0.208,0.27,0.311,0.4,0.477,0.545,0.645,0.775]},{\"type\":\"double\",\"attributes\":{},\"value\":[0,0,0,0,0,0,0,0,0,0,0,0,0,0,0]},{\"type\":\"double\",\"attributes\":{},\"value\":[0.149,0.203,0.273,0.338,0.427,0.541,0.636,0.717,0.864,1.003,1.133,1.304,1.47,1.643,1.882]},{\"type\":\"integer\",\"attributes\":{},\"value\":[524,525,526,527,528,529,530,531,532,533,534,535,536,537,538]},{\"type\":\"character\",\"attributes\":{},\"value\":[\"jags_RW\"]},{\"type\":\"character\",\"attributes\":{},\"value\":[\"exclosures\"]},{\"type\":\"character\",\"attributes\":{},\"value\":[\"PH\"]},{\"type\":\"integer\",\"attributes\":{},\"value\":[231]},{\"type\":\"character\",\"attributes\":{},\"value\":[\"231.10\"]}]}"]
