["{\"type\":\"list\",\"attributes\":{\"names\":{\"type\":\"character\",\"attributes\":{},\"value\":[\"pred\",\"interval\",\"level\",\"global\",\"type\",\"method\",\"B\",\"estim\",\"B_estim\",\"warning_messages\",\"median\",\"moon\",\"model\",\"dataset\",\"species\",\"old_cast_id\",\"cast_id\"]}},\"value\":[{\"type\":\"double\",\"attributes\":{\"tsp\":{\"type\":\"double\",\"attributes\":{},\"value\":[342,354,1]},\"class\":{\"type\":\"character\",\"attributes\":{},\"value\":[\"ts\"]}},\"value\":[2.33317484,2.59136031,2.79137345,2.94263413,3.06343442,3.15697082,3.22537357,3.27129693,3.31789794,3.34981042,3.37448309,3.39778393,3.41581103]},{\"type\":\"double\",\"attributes\":{\"dim\":{\"type\":\"integer\",\"attributes\":{},\"value\":[13,2]},\"dimnames\":{\"type\":\"list\",\"attributes\":{},\"value\":[{\"type\":\"NULL\"},{\"type\":\"character\",\"attributes\":{},\"value\":[\"lower\",\"upper\"]}]},\"tsp\":{\"type\":\"double\",\"attributes\":{},\"value\":[342,354,1]},\"class\":{\"type\":\"character\",\"attributes\":{},\"value\":[\"mts\",\"ts\",\"matrix\"]}},\"value\":[0,0,0,0,0,0,0,0,0,0,0,0,0,6,7,9,10,9,10,11,11,11,11,11,11,10]},{\"type\":\"double\",\"attributes\":{},\"value\":[0.95]},{\"type\":\"logical\",\"attributes\":{},\"value\":[false]},{\"type\":\"character\",\"attributes\":{},\"value\":[\"quantiles\"]},{\"type\":\"character\",\"attributes\":{},\"value\":[\"bootstrap\"]},{\"type\":\"double\",\"attributes\":{},\"value\":[1000]},{\"type\":\"character\",\"attributes\":{},\"value\":[\"ignore\"]},{\"type\":\"double\",\"attributes\":{},\"value\":[0]},{\"type\":\"character\",\"attributes\":{},\"value\":[]},{\"type\":\"double\",\"attributes\":{\"tsp\":{\"type\":\"double\",\"attributes\":{},\"value\":[342,354,1]},\"class\":{\"type\":\"character\",\"attributes\":{},\"value\":[\"ts\"]}},\"value\":[2,2,2,2,3,3,3,3,3,3,3,3,3]},{\"type\":\"integer\",\"attributes\":{},\"value\":[558,559,560,561,562,563,564,565,566,567,568,569,570]},{\"type\":\"character\",\"attributes\":{},\"value\":[\"nbGARCH\"]},{\"type\":\"character\",\"attributes\":{},\"value\":[\"controls\"]},{\"type\":\"character\",\"attributes\":{},\"value\":[\"DO\"]},{\"type\":\"integer\",\"attributes\":{},\"value\":[2747]},{\"type\":\"character\",\"attributes\":{},\"value\":[\"2747.3\"]}]}"]
